shortestpath/__init__.py
shortestpath/shortestpath.py
shortestpath_aybukekucuk-0.1.0.dist-info/METADATA
shortestpath_aybukekucuk-0.1.0.dist-info/WHEEL
shortestpath_aybukekucuk-0.1.0.dist-info/top_level.txt
shortestpath_aybukekucuk-0.1.0.dist-info/RECORD
