Metadata-Version: 2.4
Name: shortestpath_aybukekucuk
Version: 0.1.0
Summary: En kısa yol hesaplama modülü
Home-page: https://github.com/aaybukekucuk/shortestpath
Author: Aybuke Kucuk
Author-email: aybuke@example.com
Classifier: Programming Language :: Python :: 3
Classifier: License :: OSI Approved :: MIT License
Classifier: Operating System :: OS Independent
Requires-Python: >=3.7
Dynamic: author
Dynamic: author-email
Dynamic: classifier
Dynamic: home-page
Dynamic: requires-python
Dynamic: summary
